LICENSE.txt
MANIFEST.in
README.md
passslot.py
setup.py
passslot.egg-info/PKG-INFO
passslot.egg-info/SOURCES.txt
passslot.egg-info/dependency_links.txt
passslot.egg-info/requires.txt
passslot.egg-info/top_level.txt