Metadata-Version: 1.1
Name: passslot
Version: 0.1
Summary: PassSlot Python SDK
Home-page: http://github.com/passslot/passslot-python-sdk/
Author: PassSlot
Author-email: dev@passslot.com
License: Apache License
